litestar_api_auth/__init__.py
litestar_api_auth/__metadata__.py
litestar_api_auth/backends/__init__.py
litestar_api_auth/backends/base.py
litestar_api_auth/backends/memory.py
litestar_api_auth/backends/redis.py
litestar_api_auth/backends/sqlalchemy.py
litestar_api_auth/controllers.py
litestar_api_auth/exceptions.py
litestar_api_auth/guards.py
litestar_api_auth/middleware.py
litestar_api_auth/plugin.py
litestar_api_auth/schemas.py
litestar_api_auth/service.py
litestar_api_auth/types.py
litestar_api_auth-0.1.0.dist-info/WHEEL
litestar_api_auth-0.1.0.dist-info/METADATA
litestar_api_auth-0.1.0.dist-info/RECORD
