Metadata-Version: 2.3
Name: litestar-api-auth
Version: 0.1.0
Summary: API Key Authentication for Litestar applications
Keywords: litestar,api-key,authentication,security,middleware
Author: Jacob Coffee
Author-email: Jacob Coffee <jacob@z7x.org>
License: MIT
Classifier: Development Status :: 3 - Alpha
Classifier: Environment :: Web Environment
Classifier: Intended Audience :: Developers
Classifier: License :: OSI Approved :: MIT License
Classifier: Operating System :: OS Independent
Classifier: Programming Language :: Python
Classifier: Programming Language :: Python :: 3
Classifier: Programming Language :: Python :: 3.10
Classifier: Programming Language :: Python :: 3.11
Classifier: Programming Language :: Python :: 3.12
Classifier: Programming Language :: Python :: 3.13
Classifier: Programming Language :: Python :: 3 :: Only
Classifier: Topic :: Software Development :: Libraries :: Python Modules
Classifier: Topic :: Internet :: WWW/HTTP
Classifier: Topic :: Security
Classifier: Typing :: Typed
Requires-Dist: litestar>=2.0
Requires-Dist: litestar-api-auth[sqlalchemy,redis] ; extra == 'all'
Requires-Dist: redis>=5.0 ; extra == 'redis'
Requires-Dist: sqlalchemy>=2.0 ; extra == 'sqlalchemy'
Requires-Dist: advanced-alchemy>=0.20.0 ; extra == 'sqlalchemy'
Requires-Python: >=3.10, <3.14
Project-URL: Changelog, https://github.com/JacobCoffee/litestar-api-auth/releases/
Project-URL: Discord, https://discord.gg/litestar-919193495116337154
Project-URL: Documentation, https://jacobcoffee.github.io/litestar-api-auth
Project-URL: Homepage, https://github.com/JacobCoffee/litestar-api-auth
Project-URL: Issue Tracker, https://github.com/JacobCoffee/litestar-api-auth/issues
Project-URL: Repository, https://github.com/JacobCoffee/litestar-api-auth
Provides-Extra: all
Provides-Extra: redis
Provides-Extra: sqlalchemy
